MANIFEST.in
PYPI_README.rst
README.md
setup.cfg
setup.py
MokaPlayer.egg-info/PKG-INFO
MokaPlayer.egg-info/SOURCES.txt
MokaPlayer.egg-info/dependency_links.txt
MokaPlayer.egg-info/entry_points.txt
MokaPlayer.egg-info/not-zip-safe
MokaPlayer.egg-info/requires.txt
MokaPlayer.egg-info/top_level.txt
mokaplayer/__init__.py
mokaplayer/application.py
mokaplayer/config/__init__.py
mokaplayer/config/appconfig.py
mokaplayer/config/secret.py
mokaplayer/config/userconfig.py
mokaplayer/core/__init__.py
mokaplayer/core/library.py
mokaplayer/core/m3u_parser.py
mokaplayer/core/player.py
mokaplayer/core/queue.py
mokaplayer/core/streamer.py
mokaplayer/core/database/__init__.py
mokaplayer/core/database/album.py
mokaplayer/core/database/artist.py
mokaplayer/core/database/playlist.py
mokaplayer/core/database/song.py
mokaplayer/core/fetchers/__init__.py
mokaplayer/core/fetchers/artworks/__init__.py
mokaplayer/core/fetchers/artworks/provider_lastfm.py
mokaplayer/core/fetchers/artworks/provider_local_filesystem.py
mokaplayer/core/fetchers/lyrics/__init__.py
mokaplayer/core/fetchers/lyrics/provider_azlyrics.py
mokaplayer/core/fetchers/lyrics/provider_base.py
mokaplayer/core/fetchers/lyrics/provider_darklyrics.py
mokaplayer/core/fetchers/lyrics/provider_genius.py
mokaplayer/core/fetchers/lyrics/provider_metrolyrics.py
mokaplayer/core/fetchers/lyrics/provider_musixmatch.py
mokaplayer/core/fetchers/tabs/__init__.py
mokaplayer/core/fetchers/tabs/provider_ultimateguitar.py
mokaplayer/core/fetchers/torrents/__init__.py
mokaplayer/core/helpers/__init__.py
mokaplayer/core/helpers/event.py
mokaplayer/core/helpers/time_helper.py
mokaplayer/core/keyboard/__init__.py
mokaplayer/core/keyboard/linux.py
mokaplayer/core/keyboard/win.py
mokaplayer/core/playlists/__init__.py
mokaplayer/core/playlists/album_playlist.py
mokaplayer/core/playlists/albums_playlist.py
mokaplayer/core/playlists/artist_playlist.py
mokaplayer/core/playlists/artists_playlist.py
mokaplayer/core/playlists/m3u_playlist.py
mokaplayer/core/playlists/mostplayed_playlist.py
mokaplayer/core/playlists/rarelyplayed_playlist.py
mokaplayer/core/playlists/recentlyadded_playlist.py
mokaplayer/core/playlists/recentlyplayed_playlist.py
mokaplayer/core/playlists/songs_playlist.py
