Metadata-Version: 1.2
Name: MokaPlayer
Version: 0.8.5.7
Summary: A simple music player (GTK)
Home-page: https://github.com/vedard/MokaPlayer/
Author: Vincent Bédard
License: MIT
Keywords: mokaplayer music player tags tabs lyrics musicplayer gapless gtk
Platform: UNKNOWN
Requires-Python: >=3.6
